mindspore_gs/.commit_id
mindspore_gs/__init__.py
mindspore_gs/comp_algo.py
mindspore_gs/net_transform.py
mindspore_gs/version.py
mindspore_gs/common/__init__.py
mindspore_gs/common/box_plot.py
mindspore_gs/common/config.py
mindspore_gs/common/dumper.py
mindspore_gs/common/gs_enum.py
mindspore_gs/common/json_cache.py
mindspore_gs/common/kvcache.py
mindspore_gs/common/logger.py
mindspore_gs/common/name_prefix_tree.py
mindspore_gs/common/numpy_quant_common.py
mindspore_gs/common/print_table.py
mindspore_gs/common/register.py
mindspore_gs/common/utils.py
mindspore_gs/common/validator.py
mindspore_gs/datasets/__init__.py
mindspore_gs/datasets/base.py
mindspore_gs/datasets/boolq.py
mindspore_gs/datasets/calibrate.py
mindspore_gs/datasets/ceval.py
mindspore_gs/datasets/factory.py
mindspore_gs/datasets/gsm8k.py
mindspore_gs/datasets/squad.py
mindspore_gs/datasets/wikitext2.py
mindspore_gs/ghost/__init__.py
mindspore_gs/ghost/ghost.py
mindspore_gs/ops/__init__.py
mindspore_gs/ops/gs_custom.py
mindspore_gs/pruner/__init__.py
mindspore_gs/pruner/heads/__init__.py
mindspore_gs/pruner/heads/abstract.py
mindspore_gs/pruner/heads/factory.py
mindspore_gs/pruner/heads/supported.py
mindspore_gs/pruner/heads/type.py
mindspore_gs/pruner/heads/lrp/__init__.py
mindspore_gs/pruner/heads/lrp/abstract_lrp.py
mindspore_gs/pruner/heads/lrp/utils.py
mindspore_gs/pruner/ops/__init__.py
mindspore_gs/pruner/ops/masked_cell.py
mindspore_gs/pruner/ops/masked_conv2d.py
mindspore_gs/pruner/ops/masked_dense.py
mindspore_gs/pruner/scop/__init__.py
mindspore_gs/pruner/scop/scop_pruner.py
mindspore_gs/pruner/uni_pruning/__init__.py
mindspore_gs/pruner/uni_pruning/uni_pruner.py
mindspore_gs/pruner/uni_pruning/unipruning_masked_layer.py
mindspore_gs/pruner/uni_pruning/graph_analyzer/__init__.py
mindspore_gs/pruner/uni_pruning/graph_analyzer/equichannel_group.py
mindspore_gs/pruner/uni_pruning/graph_analyzer/graph.py
mindspore_gs/pruner/uni_pruning/graph_analyzer/graph_analyzer.py
mindspore_gs-1.4.1.dist-info/licenses/LICENSE
mindspore_gs-1.4.1.dist-info/licenses/NOTICE
mindspore_gs-1.4.1.dist-info/METADATA
mindspore_gs-1.4.1.dist-info/WHEEL
mindspore_gs-1.4.1.dist-info/top_level.txt
mindspore_gs-1.4.1.dist-info/RECORD
