Metadata-Version: 2.4
Name: mindspore_gs
Version: 1.4.1
Summary: A MindSpore model optimization algorithm set..
Home-page: https://www.mindspore.cn
Author: The MindSpore Authors
Author-email: contact@mindspore.cn
License: Apache 2.0
Keywords: mindspore optimization quantization golden-stick
Classifier: Development Status :: 4 - Beta
Classifier: Environment :: Console
Classifier: Intended Audience :: Science/Research
Classifier: Intended Audience :: Developers
Classifier: License :: OSI Approved :: Apache Software License
Classifier: Programming Language :: Python :: 3 :: Only
Classifier: Programming Language :: Python :: 3.7
Classifier: Programming Language :: Python :: 3.8
Classifier: Programming Language :: Python :: 3.9
Classifier: Programming Language :: Python :: 3.10
Classifier: Programming Language :: Python :: 3.11
Classifier: Programming Language :: C++
Classifier: Topic :: Scientific/Engineering
Classifier: Topic :: Scientific/Engineering :: Artificial Intelligence
Classifier: Topic :: Software Development
Classifier: Topic :: Software Development :: Libraries
Classifier: Topic :: Software Development :: Libraries :: Python Modules
Requires-Python: >=3.7
License-File: LICENSE
License-File: NOTICE
Requires-Dist: numpy<2.0.0,>=1.20.0
Requires-Dist: scipy>=1.5.2
Requires-Dist: pyyaml>=6.0
Requires-Dist: matplotlib>=3.9.2
Requires-Dist: prettytable>=3.7.0
Requires-Dist: datasets>=4.0.0
Requires-Dist: mindspore==2.7.1.post1
Requires-Dist: mindone>=0.5.0
Dynamic: author
Dynamic: author-email
Dynamic: classifier
Dynamic: home-page
Dynamic: keywords
Dynamic: license
Dynamic: license-file
Dynamic: requires-dist
Dynamic: requires-python
Dynamic: summary
